mons/__init__.py
mons/__main__.py
mons/baseUtils.py
mons/clickExt.py
mons/config.py
mons/downloading.py
mons/errors.py
mons/formatting.py
mons/fs.py
mons/install.py
mons/logging.py
mons/modmeta.py
mons/mons.py
mons/overlayfs.py
mons/platforms.py
mons/sources.py
mons/spec.py
mons/utils.py
mons/version.py
mons/commands/__init__.py
mons/commands/main.py
mons/commands/mods.py
mons/man/man1/mons-mods.1
mons/man/man1/mons.1
mons/man/man5/mons.5
mons/man/man7/mons-glossary.7
mons/man/man7/mons-overlayfs.7
mons-2.0.0.dist-info/LICENSE
mons-2.0.0.dist-info/METADATA
mons-2.0.0.dist-info/WHEEL
mons-2.0.0.dist-info/entry_points.txt
mons-2.0.0.dist-info/top_level.txt
mons-2.0.0.dist-info/RECORD
