Metadata-Version: 2.1
Name: mons
Version: 2.0.0
Summary: A command-line mod installer and manager for Celeste
Home-page: https://github.com/coloursofnoise/mons
Author: ColoursOfNoise
Author-email: coloursofthenoise@gmail.com
Project-URL: Documentation, https://mons.coloursofnoise.ca
Classifier: Programming Language :: Python :: 3
Classifier: License :: OSI Approved :: MIT License
Classifier: Operating System :: OS Independent
Requires-Python: >=3.8
License-File: LICENSE
Requires-Dist: dnfile
Requires-Dist: pefile
Requires-Dist: click >=8.0.2
Requires-Dist: tqdm
Requires-Dist: xxhash
Requires-Dist: pyyaml
Requires-Dist: urllib3
Requires-Dist: platformdirs
Requires-Dist: typing-extensions ; python_version < "3.10"
Requires-Dist: importlib-resources ; python_version < "3.10"
